schema_st4_parser/__init__.py
schema_st4_parser-1.0.1.dist-info/LICENSE
schema_st4_parser-1.0.1.dist-info/METADATA
schema_st4_parser-1.0.1.dist-info/WHEEL
schema_st4_parser-1.0.1.dist-info/top_level.txt
schema_st4_parser-1.0.1.dist-info/RECORD
