Metadata-Version: 2.1
Name: schema_st4_parser
Version: 1.0.1
Summary: Parse Schema ST4 xml files into pytohn objects
Author: Lukas Kreussel
License: MIT License
Project-URL: Homepage, https://github.com/LLukas22/ST4-Python-Parser
Project-URL: Bug Tracker, https://github.com/LLukas22/ST4-Python-Parser/issues
Classifier: Programming Language :: Python :: 3
Classifier: License :: OSI Approved :: MIT License
Classifier: Operating System :: OS Independent
Requires-Python: >=3.8
License-File: LICENSE
